havi/__init__.py
havi/bayes/inference.py
havi/havi.py
havi/physics/constants.py
havi/physics/model.py
havi/version.py
havi-0.1.1.dist-info/LICENSE
havi-0.1.1.dist-info/WHEEL
havi-0.1.1.dist-info/METADATA
havi-0.1.1.dist-info/RECORD
