Metadata-Version: 2.1
Name: havi
Version: 0.1.1
Summary: perform bayesian inference over physical models
License: Apache-2.0
Author: bjornaer
Author-email: maxemijo@gmail.com
Requires-Python: >=3.9,<3.11
Classifier: Development Status :: 3 - Alpha
Classifier: Intended Audience :: Science/Research
Classifier: License :: OSI Approved :: Apache Software License
Classifier: Programming Language :: Python :: 3
Classifier: Programming Language :: Python :: 3.10
Classifier: Programming Language :: Python :: 3.9
Classifier: Topic :: Scientific/Engineering :: Physics
Requires-Dist: numpy (>=1.21.5,<2.0.0)
Requires-Dist: pandas (>=1.3.5,<2.0.0)
Requires-Dist: pyro-ppl (>=1.8.0,<2.0.0)
Requires-Dist: seaborn (>=0.11.2,<0.12.0)
Requires-Dist: torch (>=1.10.1,<2.0.0)
